z3c/form/README.rst
z3c/form/__init__.py
z3c/form/action.py
z3c/form/action.rst
z3c/form/adding.py
z3c/form/adding.rst
z3c/form/apidoc.zcml
z3c/form/button.py
z3c/form/button.rst
z3c/form/button.zcml
z3c/form/configure.zcml
z3c/form/contentprovider.py
z3c/form/contentprovider.rst
z3c/form/converter.py
z3c/form/converter.rst
z3c/form/converter.zcml
z3c/form/datamanager.py
z3c/form/datamanager.rst
z3c/form/datamanager.zcml
z3c/form/error.pt
z3c/form/error.py
z3c/form/error.rst
z3c/form/error.zcml
z3c/form/events.py
z3c/form/field.py
z3c/form/field.rst
z3c/form/file.zcml
z3c/form/file_testing.zcml
z3c/form/form-chameleon-issue-repeat-addons.rst
z3c/form/form-graph.dot
z3c/form/form-graph.png
z3c/form/form-graph.ps
z3c/form/form.py
z3c/form/form.rst
z3c/form/group.py
z3c/form/group.rst
z3c/form/hint.py
z3c/form/hint.rst
z3c/form/i18n.py
z3c/form/index.rst
z3c/form/interfaces.py
z3c/form/meta.zcml
z3c/form/object-caveat.rst
z3c/form/object.py
z3c/form/object.zcml
z3c/form/outputchecker.py
z3c/form/subform.py
z3c/form/subform.rst
z3c/form/term.py
z3c/form/term.rst
z3c/form/term.zcml
z3c/form/testing.py
z3c/form/testing.rst
z3c/form/translation.zcml
z3c/form/util.py
z3c/form/util.rst
z3c/form/validator.py
z3c/form/validator.rst
z3c/form/validator.zcml
z3c/form/value.py
z3c/form/value.rst
z3c/form/widget-graph.dot
z3c/form/widget-graph.png
z3c/form/widget-graph.ps
z3c/form/widget.py
z3c/form/widget.rst
z3c/form/zcml.py
z3c/form/zcml.rst
z3c/form/browser/README.rst
z3c/form/browser/__init__.py
z3c/form/browser/button.py
z3c/form/browser/button.rst
z3c/form/browser/button.zcml
z3c/form/browser/button_display.pt
z3c/form/browser/button_input.pt
z3c/form/browser/checkbox.py
z3c/form/browser/checkbox.rst
z3c/form/browser/checkbox.zcml
z3c/form/browser/checkbox_display.pt
z3c/form/browser/checkbox_hidden.pt
z3c/form/browser/checkbox_input.pt
z3c/form/browser/configure.zcml
z3c/form/browser/file-testing.rst
z3c/form/browser/file.py
z3c/form/browser/file.rst
z3c_form-6.0.1.dist-info/LICENSE.txt
z3c_form-6.0.1.dist-info/METADATA
z3c_form-6.0.1.dist-info/WHEEL
z3c_form-6.0.1.dist-info/top_level.txt
z3c_form-6.0.1.dist-info/RECORD
