Metadata-Version: 2.2
Name: z3c.form
Version: 6.0.1
Summary: An advanced form and widget framework for Zope 3
Home-page: https://github.com/zopefoundation/z3c.form
Author: Stephan Richter, Roger Ineichen and the Zope Community
Author-email: zope-dev@zope.dev
License: ZPL-2.1
Keywords: zope3 form widget
Classifier: Development Status :: 5 - Production/Stable
Classifier: Environment :: Web Environment
Classifier: Intended Audience :: Developers
Classifier: License :: OSI Approved :: Zope Public License
Classifier: Programming Language :: Python
Classifier: Programming Language :: Python :: 3
Classifier: Programming Language :: Python :: 3.9
Classifier: Programming Language :: Python :: 3.10
Classifier: Programming Language :: Python :: 3.11
Classifier: Programming Language :: Python :: 3.12
Classifier: Programming Language :: Python :: 3.13
Classifier: Programming Language :: Python :: Implementation :: CPython
Classifier: Natural Language :: English
Classifier: Operating System :: OS Independent
Classifier: Topic :: Internet :: WWW/HTTP
Classifier: Framework :: Zope :: 3
Requires-Python: >=3.9
License-File: LICENSE.txt
Requires-Dist: setuptools
Requires-Dist: zope.browser
Requires-Dist: zope.browserpage
Requires-Dist: zope.browserresource
Requires-Dist: zope.component
Requires-Dist: zope.configuration>=4.3
Requires-Dist: zope.contentprovider
Requires-Dist: zope.event
Requires-Dist: zope.i18n
Requires-Dist: zope.i18nmessageid
Requires-Dist: zope.interface
Requires-Dist: zope.lifecycleevent
Requires-Dist: zope.location
Requires-Dist: zope.pagetemplate
Requires-Dist: zope.publisher
Requires-Dist: zope.schema>=4.7
Requires-Dist: zope.security
Requires-Dist: zope.site
Requires-Dist: zope.traversing
Provides-Extra: extra
Requires-Dist: z3c.pt>=2.1; extra == "extra"
Requires-Dist: z3c.ptcompat>=1.0; extra == "extra"
Requires-Dist: zope.pagetemplate>=3.6.2; extra == "extra"
Provides-Extra: test
Requires-Dist: lxml>=5.3; extra == "test"
Requires-Dist: persistent; extra == "test"
Requires-Dist: z3c.template>=1.3; extra == "test"
Requires-Dist: zc.sourcefactory; extra == "test"
Requires-Dist: zope.container; extra == "test"
Requires-Dist: zope.password; extra == "test"
Requires-Dist: zope.testing; extra == "test"
Provides-Extra: adding
Requires-Dist: zope.app.container>=3.7; extra == "adding"
Provides-Extra: docs
Requires-Dist: Sphinx; extra == "docs"
Requires-Dist: repoze.sphinx.autointerface; extra == "docs"
Dynamic: author
Dynamic: author-email
Dynamic: classifier
Dynamic: description
Dynamic: home-page
Dynamic: keywords
Dynamic: license
Dynamic: provides-extra
Dynamic: requires-dist
Dynamic: requires-python
Dynamic: summary
